MANIFEST.in
README.md
setup.py
examples/ja_example.py
tests/__init__.py
tests/test_interface.py
tests/test_load_entity_model.py
tests/test_make_lattice.py
tests/__pycache__/__init__.cpython-35.pyc
tests/__pycache__/test_interface.cpython-35.pyc
tests/__pycache__/test_load_entity_model.cpython-35.pyc
tests/__pycache__/test_make_lattice.cpython-35.pyc
word2vec_wikification_py/__init__.py
word2vec_wikification_py/init_logger.py
word2vec_wikification_py/initialize_mysql_connector.py
word2vec_wikification_py/interface.py
word2vec_wikification_py/load_entity_model.py
word2vec_wikification_py/make_lattice.py
word2vec_wikification_py/models.py
word2vec_wikification_py/search_wiki_pages.py
word2vec_wikification_py.egg-info/PKG-INFO
word2vec_wikification_py.egg-info/SOURCES.txt
word2vec_wikification_py.egg-info/dependency_links.txt
word2vec_wikification_py.egg-info/not-zip-safe
word2vec_wikification_py.egg-info/requires.txt
word2vec_wikification_py.egg-info/top_level.txt
word2vec_wikification_py/__pycache__/__init__.cpython-35.pyc
word2vec_wikification_py/__pycache__/init_logger.cpython-35.pyc
word2vec_wikification_py/__pycache__/initialize_mysql_connector.cpython-35.pyc
word2vec_wikification_py/__pycache__/interface.cpython-35.pyc
word2vec_wikification_py/__pycache__/load_entity_model.cpython-35.pyc
word2vec_wikification_py/__pycache__/make_lattice.cpython-35.pyc
word2vec_wikification_py/__pycache__/models.cpython-35.pyc
word2vec_wikification_py/__pycache__/search_wiki_pages.cpython-35.pyc