Metadata-Version: 1.1
Name: word2vec-wikification-py
Version: 0.11
Summary: A package to run wikification
Home-page: https://github.com/Kensuke-Mitsuzawa/word2vec_wikification_py
Author: Kensuke Mitsuzawa
Author-email: kensuke.mit@gmail.com
License: MIT
Platform: UNKNOWN
Classifier: Development Status :: 5 - Production/Stable
Classifier: License :: OSI Approved :: MIT License
Classifier: Programming Language :: Python
Classifier: Natural Language :: Japanese
Classifier: Topic :: Scientific/Engineering :: Artificial Intelligence
Classifier: Programming Language :: Python :: 3.5
